{
	"Meta(Acqusition)": {
		"doc_id": "REPORT-minute-00034",
		"doc_category": "REPORT",
		"doc_type": "minute",
		"doc_name": "제20대 국회 미래창조과학방송통신위원회 회의록 데이터셋.csv",
		"author": null,
		"publisher": null,
		"publisher_year": null,
		"doc_origin": "국회도서관 포털"
	},
	"Meta(Refine)": {
		"passage_id": "REPORT-minute-00034-00760",
		"passage": "진술인 황준호] \"예 저는 조금 다른 생각을 가지고 있습니다.\"\n박대출 위원] \"어떤 부분에서 조금 다른 것이지요?\"\n진술인 황준호] \"중복성의 문제는 말씀드렸듯이 KBS월드와……\"\n박대출 위원] \"조금 전에 통합 문제는 따로 말씀 주셨기 때문에 그것은 이 문제 풀고 말씀을 드릴게요.\"\n진술인 황준호] \"중복성을 해결하고 난 다음에 방송원 설립을 이야기한다는 것은 저의 논리적 흐름은 아닌 것 같습니다.\"\n박대출 위원] \"선후의 문제는 아니다?\"\n진술인 황준호] \"예 그러니까 공적 해외방송 국가홍보 방송이라는 것을 명확하게 정립하기 위해서는 처음부터 체계적으로 문제를 풀어 나가는 것이 가장 정답이라고 생각합니다.\"\n박대출 위원] \"그러면 서비스 측면에서 채널도 유지하고 통합도 하고 그리고 기구도 유지하는 그런 방법이 있습니까 혹시?\"\n진술인 황준호] \"글쎄요 이것도 저것도 다 좋은 방법을 만들기란 쉽지 않겠지만 현재 저는 KBS가 운영하고 있는 KBS월드와 KBS라디오는 굉장히 다른 성격입니다. 아리랑국제방송은 KBS월드TV하고는 또 다른 성격입니다. 그러니까 통합을 논의할 때는 기구 통합만이 아니라 채널 운영 채널 전략까지도 함께 고려해야 되는 통합 운영 방안이 필요하다고 생각합니다.\"\n박대출 위원] \"채널 운영과 관련해서 그러면 황준호 진술인께서는 기존 채널을 유지하는 상태가 좋습니까 아니면 기존 채널도 통합하는 것까지도 검토해야 됩니까?\"\n",
		"passage_Cnt": 706
	},
	"Annotation": {
		"summary1": "황 진술인은 KBS 월드와 KBS 라디오는 다른 성격이라 통합을 논의할 때 기구 통합과 채널 운영 채널 전략도 고려하는 통합 운영 방안이 필요하다고 말했다.",
		"summary2": "진술인 황준호] \"글쎄요 이것도 저것도 다 좋은 방법을 만들기란 쉽지 않겠지만 현재 저는 KBS가 운영하고 있는 KBS월드와 KBS라디오는 굉장히 다른 성격입니다. 그러니까 통합을 논의할 때는 기구 통합만이 아니라 채널 운영 채널 전략까지도 함께 고려해야 되는 통합 운영 방안이 필요하다고 생각합니다.",
		"summary3": null,
		"summary_3_cnt": null
	}
}