{
	"Meta(Acqusition)": {
		"doc_id": "REPORT-minute-00035",
		"doc_category": "REPORT",
		"doc_type": "minute",
		"doc_name": "제20대 국회 법제사법위원회 회의록 데이터셋.csv",
		"author": null,
		"publisher": null,
		"publisher_year": null,
		"doc_origin": "국회도서관 포털"
	},
	"Meta(Refine)": {
		"passage_id": "REPORT-minute-00035-04770",
		"passage": "이완영 위원] \"추진을 하실 겁니까?\"\n환경부장관 조명래] \"지금 검토 중입니다.\"\n이완영 위원] \"검토 중에 있다?\"\n환경부장관 조명래] \"예 검토 중인데……\"\n이완영 위원] \"신중하게…… 실효성 문제가 제기되고 있습니다.\"\n환경부장관 조명래] \"예 알고 있습니다.\"\n이완영 위원] \"신중하게 판단을 하시고……\"\n환경부장관 조명래] \"예 그것은 도시 전체에 적용하기보다도 미세먼지 고농도가 계속되는 동안 특히 도심에 이를테면 빌딩에 공기가 갇혀 있거나 특히 고농도가 집중적으로 지속되고 있는 그런 지역에 우심지역이라고 하는 지역에 대해서 일시적으로 좀 공기를 정화할 수 있는 제한적 효과를 갖는 그런 것이라고 저희들은 보고 있고요. 기술적 검토를 통해서는 어느 정도 가능하다고 보지만 실증을 안 해 봤기 때문에 아직까지는 저희들이 대외적으로 이것을 하겠다고 하기보다는 시범사업으로 먼저 해 보겠다 이렇게 발표를 했던 겁니다.\"\n이완영 위원] \"그래도 5000억 예산이 발표되고 하니까 혈세가 효과 없이 낭비되는 일은 없어야 되겠다……\"\n환경부장관 조명래] \"예 명심하겠습니다.\"\n이완영 위원] \"조금만 더 하겠습니다.\"\n위원장 여상규] \"예.\"\n이완영 위원] \"교육부장관님!\"\n부총리겸교육부장관 유은혜] \"예.\"\n이완영 위원] \"학교보건법요. 신설되는 4조의2는 상ㆍ하반기별로 1회 이상으로 돼 있고 기존의 4조에는 연 1회 돼 있지 않습니까? 이것 조정을 해야 되는 것 아니에요?\"\n",
		"passage_Cnt": 720
	},
	"Annotation": {
		"summary1": "조 장관은 기술적 검토를 통해서 우심지역에 일시적인 공기 정화가 가능하다고 보지만 실증을 안 해봐서 시범사업으로 발표했다고 했다.",
		"summary2": "환경부장관 조명래] \"예 그것은 도시 전체에 적용하기보다도 미세먼지 고농도가 계속되는 동안 특히 도심에 이를테면 빌딩에 공기가 갇혀 있거나 특히 고농도가 집중적으로 지속되고 있는 그런 지역에 우심지역이라고 하는 지역에 대해서 일시적으로 좀 공기를 정화할 수 있는 제한적 효과를 갖는 그런 것이라고 저희들은 보고 있고요. 기술적 검토를 통해서는 어느 정도 가능하다고 보지만 실증을 안 해 봤기 때문에 아직까지는 저희들이 대외적으로 이것을 하겠다고 하기보다는 시범사업으로 먼저 해 보겠다 이렇게 발표를 했던 겁니다.",
		"summary3": null,
		"summary_3_cnt": null
	}
}