{
	"Meta(Acqusition)": {
		"doc_id": "REPORT-minute-00031",
		"doc_category": "REPORT",
		"doc_type": "minute",
		"doc_name": "제20대 국회 기획재정위원회 회의록 데이터셋.csv",
		"author": null,
		"publisher": null,
		"publisher_year": null,
		"doc_origin": "국회도서관 포털"
	},
	"Meta(Refine)": {
		"passage_id": "REPORT-minute-00031-02921",
		"passage": "위원장 정성호] \"추경호 위원님 좋은 말씀 주셨습니다.  다음 윤후덕 위원님 보충질의 마지막 순서로 질의하시겠습니다.\"\n윤후덕 위원] \"통계청장님 고용동향 지표 이 보도자료 내고 엄청 유명해졌네요. 그렇지요?\"\n통계청장 황수경] \"제가 유명한 것은 아니고 통계청이 유명해졌습니다.\"\n윤후덕 위원] \"취업자 수 증가라는 고용동향 지표를 다른 나라들도 많이 사용하나요?\"\n통계청장 황수경] \"전년 대비 증감 수 말씀하시는 것이라면……\"\n윤후덕 위원] \"그렇지요. 전년 동월 대비 취업자 수 증감이라는 고용동향 지표를 다른 나라들도 많이 사용해요?\"\n통계청장 황수경] \"사용할 수는 있습니다만 의미는 좀 다르다고 생각을 합니다. 왜냐하면 취업자 수를 지표로 인정한다는 것은 모수가 거의 동일한 조건에 있다 이런 것을 전제로 해서 얘기를 하는 것인데요. 한국의 상황은……\"\n윤후덕 위원] \"그러니까요.   여러 나라의 경우를 비교한다 하더라도 인구가 증가하는 나라가 있고 인구가 정체된 나라가 있고 인구가 감소하는 나라가 있고 한 나라 안에서도 일정 국면에서는 인구가 증가하기도 하고 정체하기도 하고 우리 같은 경우에는 15세 이상 생산가능인구가 줄어들고 있는 추세인 것 아닙니까? 제가 보기에는 그런 요인들을 가감 삭제를 해야 하는 통계지표로밖에 안 보여요.\"\n통계청장 황수경] \"맞습니다. 그래서 저희가 지난달에 특별한 백브리핑을 했었는데요. 그러니까 여러분들이 인구 변화라고 하는 게 사실은 그렇게 갑작스럽게 일어날 것이라고 생각을 못 하실 것 같지만 실제로는 엄청나게 빠른 속도로 인구 구성을 바꾸고 있습니다.   그래서 제가 한 가지만 더 말씀드리면 예를 들어서 취업자 수로 봤을 때는 굉장히 크게 오해를 할 수 있는 부분이 있습니다. 예컨대 청년층 일자리가 감소하고 있다라든가 그다음에 고졸자 일자리가 감소하고 있다라든가 이런 부분은 이것은 너무나 당연한 얘기입니다. 지표로 얘기하는 게 아닙니다.\"\n",
		"passage_Cnt": 954
	},
	"Annotation": {
		"summary1": "윤 위원이 취업자 수 증가라는 고용동향 지표를 다른 나라에서도 많이 사용하냐고 묻자 황 통계청장은 사용할 수는 있으나 한국의 상황과는 다르다고 말했다.",
		"summary2": "윤후덕 위원] \"취업자 수 증가라는 고용동향 지표를 다른 나라들도 많이 사용하나요?\" 통계청장 황수경] \"사용할 수는 있습니다만 의미는 좀 다르다고 생각을 합니다. 한국의 상황은……",
		"summary3": null,
		"summary_3_cnt": null
	}
}