{
	"Meta(Acqusition)": {
		"doc_id": "REPORT-minute-00035",
		"doc_category": "REPORT",
		"doc_type": "minute",
		"doc_name": "제20대 국회 법제사법위원회 회의록 데이터셋.csv",
		"author": null,
		"publisher": null,
		"publisher_year": null,
		"doc_origin": "국회도서관 포털"
	},
	"Meta(Refine)": {
		"passage_id": "REPORT-minute-00035-01164",
		"passage": "국방부장관 한민구] \"북한이 되겠습니다.\"\n위원장 권성동] \"북한과 중국이라고 생각합니다.\"\n국방부장관 한민구] \"중국도 좋아할 것입니다.\"\n위원장 권성동] \"중국이 ‘우리가 한마디 에헴 하고 기침하면 대한민국이 꼼짝 못하는구나’ 이것이 이제 시금석이 돼 가지고 출발점이 돼 가지고 아마 중국이 어떤 사안이든 간에 대한민국을 좌지우지하려 들 것입니다.  그런데 사실 북한의 핵과 미사일에 대응할 만한 무기 체계를 우리 자신이 갖고 있지 못합니다. 그렇지요?\"\n국방부장관 한민구] \"저희들이 갖고 있습니다마는 제한되는 면이 있습니다.\"\n위원장 권성동] \"그러니까요 완벽하게 대응하기가 어려운 거예요.  이번에 12일 날 발사했던 미사일도 사거리가 얼마나 됩니까?\"\n국방부장관 한민구] \"사거리는 이번에는 고각발사를 해서 한 500㎞ 탄착을 했는데……\"\n위원장 권성동] \"실제.\"\n국방부장관 한민구] \"실제 그것을 최소 사거리로 하면 제가 정확하게 말씀 안 드린 것은 탄도의 중량을 얼마로 하느냐에 따라서 사거리가 많이 달라지기 때문에 말씀을 안 드렸습니다.\"\n위원장 권성동] \"하여튼 500㎞ 1000㎞ 이상은 되는 것 아닙니까 솔직히?\"\n국방부장관 한민구] \"그렇습니다.\"\n위원장 권성동] \"그래서 결국은 이것을 방어하는 무기 시스템이 사드밖에 없다고 하니까 이것 배치를 해야 됩니다.  그리고 배치하겠다고 그러는데 상주에 배치하겠다는데 지금 협상 과정이 어떻게 돼 가고 있습니까 롯데하고 이 과정이?\"\n",
		"passage_Cnt": 730
	},
	"Annotation": {
		"summary1": "권 위원장은 사드를 배치하기 위한 협상 과정이 어떻게 되어가고 있냐고 물었다.",
		"summary2": "위원장 권성동] \"그래서 결국은 이것을 방어하는 무기 시스템이 사드밖에 없다고 하니까 이것 배치를 해야 됩니다. 그리고 배치하겠다고 그러는데 상주에 배치하겠다는데 지금 협상 과정이 어떻게 돼 가고 있습니까 롯데하고 이 과정이?",
		"summary3": null,
		"summary_3_cnt": null
	}
}