{
	"Meta(Acqusition)": {
		"doc_id": "REPORT-minute-00035",
		"doc_category": "REPORT",
		"doc_type": "minute",
		"doc_name": "제20대 국회 법제사법위원회 회의록 데이터셋.csv",
		"author": null,
		"publisher": null,
		"publisher_year": null,
		"doc_origin": "국회도서관 포털"
	},
	"Meta(Refine)": {
		"passage_id": "REPORT-minute-00035-02843",
		"passage": "박지원 위원] \"저는 전문가가 아니니까 모릅니다. 그렇지만 금과 은으로 거래를 할 때 ‘종이가 무슨 돈이냐’라고 했지만 지폐가 지금 다 사용되고 있어요. 가상화폐를 지금은 ‘화폐가 아니다’라고 하지만 그 시대로 넘어갈 수 있어요.  그래서 저는 금융위원장께서 조금 주도적으로 블록체인 같은 것은 또 과학기술정보통신부에서 한다 하고 단속은 또 해야 되고 물론 규제해야지요. 그렇기 때문에 확실한 방향을……    (발언시간 초과로 마이크 중단)    (마이크 중단 이후 계속 발언한 부분)  물론 자꾸 변하니까 별수 없지만 자꾸 국민들한테 설명하고 특히 해킹의 불안에 대해서 우려가 얼마나 큽니까? 북한도 우리 해킹해서 그것 빠져나갔을 때 어떻게 할 것이냐? 이런 문제를 철저히 대비해 주시기 바랍니다.\"\n금융위원장 최종구] \"예 잘 알겠습니다.\"\n위원장 권성동] \"수고하셨습니다.  다음 윤상직 위원님 질의하시기 바랍니다.\"\n윤상직 위원] \"금융위원장 말이지요 지금도 답변 중에 가상화폐거래소에서 거래하는 것을 갖다가 투기라고 하셨거든요. 투기라고 하셨어요.\"\n금융위원장 최종구] \"예 투기적인 양상이 많이 나타나고 있습니다.\"\n윤상직 위원] \"그 부분에 대해서 2030세대들은 이해를 못 합니다. 투기적이다라는 시각에서 하니까 규제 일변도가 나오는 것이지요. 그러면서도 또 정부가 정책 일관성도 가지지 못하면서 오락가락했잖아요.   컨트롤타워 제대로 했어요? 국무조정실에서 컨트롤타워 한다 그러는데 금융위원장은 ‘화폐가 아니다’ 해서 뒤로 빠져 버리고 국무조정실은 뭘 합니까? 그냥 차관회의 정도 하는 것이지.\"\n",
		"passage_Cnt": 791
	},
	"Annotation": {
		"summary1": "박 위원이 블록체인은 과학기술정보통신부에서 하고 최 금융위원장은 주도적으로 단속과 규제를 해야 한다고 말하자 최 금융위원장이 알겠다고 답했다.",
		"summary2": "박지원 위원] \"저는 전문가가 아니니까 모릅니다. 그래서 저는 금융위원장께서 조금 주도적으로 블록체인 같은 것은 또 과학기술정보통신부에서 한다 하고 단속은 또 해야 되고 물론 규제해야지요. 금융위원장 최종구] \"예 잘 알겠습니다.\"",
		"summary3": null,
		"summary_3_cnt": null
	}
}