{
	"Meta(Acqusition)": {
		"doc_id": "REPORT-minute-00032",
		"doc_category": "REPORT",
		"doc_type": "minute",
		"doc_name": "제20대 국회 농림축산식품해양수산위원회 회의록 데이터셋.csv",
		"author": null,
		"publisher": null,
		"publisher_year": null,
		"doc_origin": "국회도서관 포털"
	},
	"Meta(Refine)": {
		"passage_id": "REPORT-minute-00032-00973",
		"passage": "농림축산식품부장관 김재수] \"그래서 저희들은 여러 협상 틀이 정해지면 구체적 품목별로 영향도 분석하고……  저희들이 FTA를 적극적으로 하자는 자세는 아닙니다.    (발언시간 초과로 마이크 중단)    (마이크 중단 이후 계속 발언한 부분)\"\n박완주 위원] \"분석한 게 다 있는데 뭘 또 이제 와서 분석한다고 그래요.\"\n농림축산식품부장관 김재수] \"아니요 이것은 하기 전에 분석한 거고 협상의 틀을 어떤 품목을 중심으로 하고 협상 내용은 어떻게 하고 관세의 삭감은 어떻게 하는 것들에 대한 구체적인 게 나올 때……\"\n박완주 위원] \"내줄 생각은 있으시구먼요 장관님은.\"\n농림축산식품부장관 김재수] \"기본적인 여러 가지 정책은 있습니다.\"\n박완주 위원] \"그러니까 기본적으로는 내주실 생각은 있으신 거야 농산물에 대해서 추가 개방을. 그렇지요?\"\n농림축산식품부장관 김재수] \"내준다는 표현은 좀 그런데요 저희들이 DDA 협상 이후에 하자고 미루어 놓았던 것이 391개 품목입니다. 그래서 그런 품목에 대해서 추가로 요구가 있을 거니까 그에 대해서 대비를 하자. 그리고 어떤 품목에 집중적으로 요구를 하면 그 품목은 또 어떤 전략으로 하고 보완 대책은 또 어떻게 하자 이런 것들을 앞으로 쭉 협의를 해 나갈 겁니다.\"\n박완주 위원] \"그러니까 기본적으로 우리 장관님은 추가로 농산물도 내줄 수 있다 필요에 따라서는?\"\n농림축산식품부장관 김재수] \"전체적으로 이익이 더 크다고 판단될 때는 우리가 또 일부 분야에서 양보도 해야 되는 것이 현실입니다.\"\n",
		"passage_Cnt": 755
	},
	"Annotation": {
		"summary1": "박 위원이 필요에 따라 농산물을 추가 개방할 생각인지 묻자 김 농림축산식품부장관은 전체적으로 이익이 더 크다고 판단될 때는 일부 분야에서 양보도 해야 하는 것이 현실이라고 했다.",
		"summary2": "박완주 위원] \"그러니까 기본적으로는 내주실 생각은 있으신 거야 농산물에 대해서 추가 개방을. 박완주 위원] \"그러니까 기본적으로 우리 장관님은 추가로 농산물도 내줄 수 있다 필요에 따라서는?\" 농림축산식품부장관 김재수] \"전체적으로 이익이 더 크다고 판단될 때는 우리가 또 일부 분야에서 양보도 해야 되는 것이 현실입니다.\"",
		"summary3": null,
		"summary_3_cnt": null
	}
}