{
	"Meta(Acqusition)": {
		"doc_id": "REPORT-minute-00035",
		"doc_category": "REPORT",
		"doc_type": "minute",
		"doc_name": "제20대 국회 법제사법위원회 회의록 데이터셋.csv",
		"author": null,
		"publisher": null,
		"publisher_year": null,
		"doc_origin": "국회도서관 포털"
	},
	"Meta(Refine)": {
		"passage_id": "REPORT-minute-00035-04527",
		"passage": "송기헌 위원] \"그런데도 제가 이 내용을 보니까 이상한 것도 많이 있어요.  법령용어 정비위원회 위원 수당이 작년에는 한 번에 20만 원이었는데 이번에 40만 원으로 한꺼번에 2배가 올라갔어요 그렇지요?\"\n법제처장 김외숙] \"1인당 한 번에 40만 원이라는 뜻은 아닐 것 같습니다.\"\n송기헌 위원] \"회의비가 1회 40만 원이라고 되어 있는 것 같은데요 작년에서는 20만 원이었는데. 한번 잘 보시고요.  회의하는 데 시간이 얼마나 걸리는지 한번 보시고 회의에 참석하시는 분들이 변호사들인지 전문가들인지 변호사들은 1시간에 수십만 원도 받고 100만 원 이상도 받아요. 그렇지요? 아시지요?\"\n법제처장 김외숙] \"예 그렇기는 하지만 저희가 한 번에 40만 원씩……\"\n송기헌 위원] \"그러니까 금액 그 자체가 많다 적다 평가할 문제가 아니라는 얘기고 실제로 회의하는 데 얼마나 시간이 걸리는지 그걸 잘 보셔야 될 것 같고요.  그리고 이게 올해 한 해만 되는 것 같지만 이게 계속 해 가지고 이어지는 걸로 되어 있지요?\"\n법제처장 김외숙] \"예 알기 쉬운 법령 만들기……\"\n송기헌 위원] \"저는 처장님과 법제처한테 말씀드리고 싶은 것이 전체적으로 업무량이 얼마나 되는지를 제시하셔야 될 것 같아요. 검토를 해 가지고 해야 될 법이 지금 몇 개가 있는지 몇 개 이상 하시는지……\"\n법제처장 김외숙] \"법률제명약칭위원회 말씀하시는 건가요?\"\n송기헌 위원] \"아니요 알기 쉬운 법령 만들기 사업 이 사업 대상이 되는 법령이 대략 몇 개 정도 되는지를 아마 잘 제시를 하셔야 되고……\"\n",
		"passage_Cnt": 771
	},
	"Annotation": {
		"summary1": "송 위원이 법령용어 정비위원회 위원 수당이 한꺼번에 2배가 올랐다고 하자 김 처장은 1인당 한 번에 40만 원이라는 뜻은 아닌 것 같다고 했다.",
		"summary2": "송기헌 위원] \"그런데도 제가 이 내용을 보니까 이상한 것도 많이 있어요. 법령용어 정비위원회 위원 수당이 작년에는 한 번에 20만 원이었는데 이번에 40만 원으로 한꺼번에 2배가 올라갔어요 그렇지요? 법제처장 김외숙] \"1인당 한 번에 40만 원이라는 뜻은 아닐 것 같습니다.\"",
		"summary3": null,
		"summary_3_cnt": null
	}
}