{
	"Meta(Acqusition)": {
		"doc_id": "REPORT-minute-00035",
		"doc_category": "REPORT",
		"doc_type": "minute",
		"doc_name": "제20대 국회 법제사법위원회 회의록 데이터셋.csv",
		"author": null,
		"publisher": null,
		"publisher_year": null,
		"doc_origin": "국회도서관 포털"
	},
	"Meta(Refine)": {
		"passage_id": "REPORT-minute-00035-00314",
		"passage": "헌법재판소사무처장 김용헌] \"고등학교를 어디 나왔느냐 이런 것을 보는 것은 아니고 대학교도 그런 것 보는 것은 아니고 다만 기본적인 학력을 아는 것은 하나의 그 사람의 전인적인 평가 요소가 아닌가 이런 생각은 됩니다.\"\n노회찬 위원] \"사실은 이것 자체가 그렇지 않습니까? 우리가 생선을 구매할 때 고등어 이것이 국내산인지 아니면 해외에서 수입한 것인지만 따지지 이것이 거제도 앞바다에서 잡혔는지 흑산도 앞바다에서 잡혔는지까지 기재하지 않지 않습니까? 불필요한 오해를 낳을 수 있는 소지를 없애야 되지 않겠습니까?\"\n헌법재판소사무처장 김용헌] \"예 계속 검토하겠습니다.\"\n노회찬 위원] \"검토를 해 보시기 바랍니다.\"\n헌법재판소사무처장 김용헌] \"예.\"\n노회찬 위원] \"양심적 병역거부 사건과 관련해서 조금 전에도 질의가 있었습니다마는 OECD 국가 중에서 양심적 병역거부를 차별하는 나라가 대한민국뿐이라는 사실을 알고 계십니까?\"\n헌법재판소사무처장 김용헌] \"예 위원님이 말씀하시니까……\"\n노회찬 위원] \"이미 몇 차례의 헌법재판소 결정이 있었습니다마는 시대가 변하고 있지 않습니까? 지금 접수된 사건이 여러 건이 있는데 그중에 가장 먼저 접수된 것은 2011년 것이지요?\"\n헌법재판소사무처장 김용헌] \"예.\"\n노회찬 위원] \"거의 5년이 지나고 있는데……\"\n헌법재판소사무처장 김용헌] \"지난번 결정하자마자 바로 또 들어온 것입니다.\"\n노회찬 위원] \"들어온 것인데 이미 5년이 지났고 그간에 변론은 한 번밖에 없었지요?\"\n",
		"passage_Cnt": 742
	},
	"Annotation": {
		"summary1": "노 위원은 시대가 변하고 있는데 OECD 국가 중에서 양심적 병역거부를 차별하는 나라는 대한민국뿐이라고 말했다.",
		"summary2": "노회찬 위원] \"양심적 병역거부 사건과 관련해서 조금 전에도 질의가 있었습니다마는 OECD 국가 중에서 양심적 병역거부를 차별하는 나라가 대한민국뿐이라는 사실을 알고 계십니까?\" 노회찬 위원] \"이미 몇 차례의 헌법재판소 결정이 있었습니다마는 시대가 변하고 있지 않습니까?",
		"summary3": null,
		"summary_3_cnt": null
	}
}