{
	"Meta(Acqusition)": {
		"doc_id": "REPORT-minute-00033",
		"doc_category": "REPORT",
		"doc_type": "minute",
		"doc_name": "제20대 국회 문화체육관광위원회 회의록 데이터셋.csv",
		"author": null,
		"publisher": null,
		"publisher_year": null,
		"doc_origin": "국회도서관 포털"
	},
	"Meta(Refine)": {
		"passage_id": "REPORT-minute-00033-00225",
		"passage": "국립중앙박물관기획운영단장 김철민] \"예.\"\n위원장대리 손혜원] \"여기서는 고려의 금속공예만 가지고 전시하고 있습니다. 제가 박물관장을 만나 뵙고 잠시 얘기를 들었는데 도대체 고려의 금속공예가 어떤 정도의 수준이었는지 무엇인지 국박에서 그것을 분석하고 계십니까? 예산 올라온 것 보면 맨 VR이니 디지털을 한다고는 계속 예산을 올리시는데 왜 이런 연구활동을 안 하십니까? 왜 이런 전문가들을 키우지 않으십니까? 1100년에 제 연도에도 제대로 못하는 이런 전시를 하는 데 예산을 얼마나 쓰십니까? 이것 지금 내용도 모르셨잖아요. 일본에서 이들이 10년을 넘게 준비해서 고려전 1100년 하고 있는 것 다시 한번……  이것 보십시오.  금속공예 ‘건국 1100년 금속공예의 빛과 신앙’ 대고려전이 아니고요.  그다음에 네이라쿠미술관의 고려 상감청자와 자기 소장품들입니다. 청자와 그리고 조선 분청사기를 섞어서 같이 도자전을 하고 있습니다.  그리고 이분들이 일하는 것들을 쭉 보시고요. 한번…… 어떤 생각을 해야 될지 참 난감한데요. 지금 이 상황에서 이분들이 일본에서 주제를 걸고 있는 것이 ‘고결’입니다. 최고의 찬사지요 고려 공예에 대해서 고려의 유물에 대해서. 고결이라는 주제로 전국에서 열리고 있습니다. 하나하나가 그렇게 위대할 수가 없습니다.  1100년 전의 고려 건국……    (발언시간 초과로 마이크 중단)  1분만 더 쓸게요 일단 조금만 하고요.  여기서 여러 곳에서 지금 전시를 하고 있는데 큐레이터들이 얼마나 심도 있는 연구를 했는지 그리고 좋은 전시를 하기 위해서 역량을 갖춘 전문가들이 모여 있는지 좀 알아보시기 바랍니다.  그리고 덕분에 일본 시민들은 고려에 대해서 굉장히 잘 알고 있습니다 청자뿐 아니라. 고려에 대해서 굉장히 큰 사랑을 갖고 있다는 것이지요. 물론 고려보다 일본 사람들이 더 좋아하는 시대는 백제지요.  고려 1100년을 준비하는데요 우리 김치 대신 기무치가 세계에 등록되어 있습니다. 저는 고려가 그렇게 될까 봐 참으로 걱정입니다.  박물관은 해야 되는 본인들의 가야 될 길이 있습니다. 왜 그 길은 제대로 못 가면서 계속 VR…… VR 해서 박물관 가뜩이나 사람 없는데 더 못 오게 만드시게요? 집에서 VR 켜 놓고 보게 하시게요?  오늘 우리나라에 국립감정원이 생긴 지 50년이 되는 날입니다. 그들이 모두가 알아요. 유물을 직접 바라볼 때 받는 기운이 있습니다. 박물관에는 어린 아이들과 사람들이 국민들이 와서 그것을 보게 해야 됩니다.  이번에 김영주 위원님 보셨겠지만 동경 국립박물관이나 정창원 박물관에 줄 서서 들어가는 인산인해의 사람들을 보면서 저는 참 가슴이 미어지더라고요 우리 박물관의 썰렁함에.  그리고 이 전시를 이제 1100년을 다 보내는 12월에 오픈한다라는 이 미비한 준비에 대해서 어떻게 해야 될지……  그런데 지금 말씀이 충분히 1년을 준비했다고요? 일본은 10년을 준비했다고 합니다.\"\n",
		"passage_Cnt": 1434
	},
	"Annotation": {
		"summary1": "손 위원장대리는 VR이 아닌 국민들이 와서 고려의 금속공예를 보게 해야 된다고 말했다.",
		"summary2": "위원장대리 손혜원] \"여기서는 고려의 금속공예만 가지고 전시하고 있습니다. VR 해서 박물관 가뜩이나 사람 없는데 더 못 오게 만드시게요? 박물관에는 어린 아이들과 사람들이 국민들이 와서 그것을 보게 해야 됩니다.",
		"summary3": null,
		"summary_3_cnt": null
	}
}