{
	"Meta(Acqusition)": {
		"doc_id": "REPORT-minute-00031",
		"doc_category": "REPORT",
		"doc_type": "minute",
		"doc_name": "제20대 국회 기획재정위원회 회의록 데이터셋.csv",
		"author": null,
		"publisher": null,
		"publisher_year": null,
		"doc_origin": "국회도서관 포털"
	},
	"Meta(Refine)": {
		"passage_id": "REPORT-minute-00031-03902",
		"passage": "권성동 위원] \"후보자님 지금 국세청장 임기가 있습니까?\"\n국세청장후보자 김현준] \"없습니다.\"\n권성동 위원] \"없지요?\"\n국세청장후보자 김현준] \"예 그렇습니다.\"\n권성동 위원] \"그러니까 청와대에서 오라면 오고 총리실에서 오라면 오는 거예요.  유치원총연합회가 한유총이 뭐 하는 데예요? 교육부의 유아교육정책에 반기를 든 것 아닙니까? 그렇다고 해 가지고 그 대책회의를 하는 데 국세청이 왜 갑니까? 왜 갔겠어요? 한승희 청장이 왜 갔겠어? 좀 더 오래 국세청장 직위를 유지하고 싶어서 가는 거예요. 청와대 지시로 회의를 하는 데 안 가면 잘릴까 봐. 국세청장 자리를 이렇게 취약하게 만들어 놨어요.   우리 당의 심재철 위원님이 2년 임기 보장하는 개정안 냈는데 아직 통과가 안 되고 있는 거예요. 이것 하루빨리 임기제로 해야 됩니다. 그래야 소신 있는 국세행정 펼칠 수 있는 거예요.  그렇기 때문에 청장후보자께서…… 청장후보자도 마찬가지예요. 지금 젊은 나이에 국세청장이 되는데 청와대에 밉보였다가 언제 잘릴지도 모르는데 이 어려운 청문회 통과해서 국세청장에 임명되는데 정치적인 세무조사 안 한다? 저는 그것 믿지 않습니다. 분명히 청와대 시키면 ‘예 알겠습니다’ 할 거예요.   그것은 어느 정도 시일이 지나면 했는지 안 했는지 드러날 것이다 나는 이렇게 생각을 하고 있습니다. 말이라도 안 하겠다 그러니까 한번 지켜보겠습니다.   그리고 지금 국세를 부과해 가지고 심사청구 조세심판청구 조세소송 해 가지고 이게 도대체 패소율이 조세소송만 삼십몇 %야 39%. 어떻게 이런 일이 가능하지요?\"\n",
		"passage_Cnt": 786
	},
	"Annotation": {
		"summary1": "권 위원은 국세청장이 청와대에서 오라면 오고 총리실에서 오라면 와야 할 만큼 자리가 취약하게 만들어져 있으니 하루 빨리 임기제로 해야 한다고 말했다.",
		"summary2": "권성동 위원] \"그러니까 청와대에서 오라면 오고 총리실에서 오라면 오는 거예요. 국세청장 자리를 이렇게 취약하게 만들어 놨어요. 이것 하루빨리 임기제로 해야 됩니다.",
		"summary3": null,
		"summary_3_cnt": null
	}
}