{
	"Meta(Acqusition)": {
		"doc_id": "REPORT-minute-00035",
		"doc_category": "REPORT",
		"doc_type": "minute",
		"doc_name": "제20대 국회 법제사법위원회 회의록 데이터셋.csv",
		"author": null,
		"publisher": null,
		"publisher_year": null,
		"doc_origin": "국회도서관 포털"
	},
	"Meta(Refine)": {
		"passage_id": "REPORT-minute-00035-00515",
		"passage": "법무부장관 김현웅] \"전혀 저는 그런 사안에 대해서 알지 못할 뿐 아니라……\"\n조응천 위원] \"변찬우 전 검사장이……\"\n법무부장관 김현웅] \"변찬우 전 검사장이 어떤 취지로 저런 말을 하였는지 또 한 게 사실인지 확인을 거쳐야 될 사안으로 봅니다.\"\n조응천 위원] \"검사로서 옷을 벗고 나가 가지고 한 거예요.   또 이 내용을 보면 변찬우 검사장하고 이정현 전 수석 간의 주장에……    (발언시간 초과로 마이크 중단)    (마이크 중단 이후 계속 발언한 부분)공통점이 있습니다. ‘해경에 대해서 책임을 묻지 말라는 것’ 그런 공통점이 있습니다.   결국 정치적 사건이나 사회적 이목이 집중된 사건 정권이 아파야 할 사건에 대해 가지고는 청와대 가이드라인이 작동하고 있다 이렇게 보입니다.  오후에 다시 하겠습니다.\"\n위원장 권성동] \"수고하셨습니다.   다음은 존경하는 오신환 위원님 질의해 주시기 바랍니다.\"\n오신환 위원] \"서울 관악을 출신 오신환 위원입니다.  법무부 관련 여러 현안들이 쟁점이 많아서 오늘 의사일정 중심보다는 현안 중심으로 많은 질의가 있을 것 같습니다.   하지만 저는 오늘 2015 회계연도 결산 그리고 예비비지출 승인의 건 관련한 의사일정에 집중해서 몇 가지 질의드리도록 하겠습니다.   작년 특별감찰관 조직이 생기면서 예산이 법무부의 예비비에서 쓰여지고 있었지요?\"\n법무부장관 김현웅] \"예 그렇습니다.\"\n오신환 위원] \"앞서 장관님께서 결산과 관련해서 발언한 내용 중에는 사실 특별감찰관 예산 관련한 내용은 없습니다. 그렇지요?\"\n",
		"passage_Cnt": 766
	},
	"Annotation": {
		"summary1": "조 위원은 김 법무부장관에게 정치적 사건이나 사회적 이목이 집중된 사건 정권이 아파야 할 사건에 대해서는 청와대 가이드라인이 작동하고 있다고 했다.",
		"summary2": "법무부장관 김현웅] \"변찬우 전 검사장이 어떤 취지로 저런 말을 하였는지 또 한 게 사실인지 확인을 거쳐야 될 사안으로 봅니다.\" 조응천 위원] \"검사로서 옷을 벗고 나가 가지고 한 거예요. 결국 정치적 사건이나 사회적 이목이 집중된 사건 정권이 아파야 할 사건에 대해 가지고는 청와대 가이드라인이 작동하고 있다 이렇게 보입니다.",
		"summary3": null,
		"summary_3_cnt": null
	}
}