{
	"Meta(Acqusition)": {
		"doc_id": "REPORT-minute-00002",
		"doc_category": "REPORT",
		"doc_type": "minute",
		"doc_name": "제19대 국회 교육문화체육관광위원회 회의록 데이터셋.csv",
		"author": null,
		"publisher": null,
		"publisher_year": null,
		"doc_origin": "국회도서관 포털"
	},
	"Meta(Refine)": {
		"passage_id": "REPORT-minute-00002-02707",
		"passage": "교육부장관후보자 김명수] \"우리 사회에 일반적으로 적용될 수 있는 것도 있고 그러나 학회의 기준에 따라서 달라질 수도 있는 것도 있고 저는 그렇다고 생각합니다.\"\n유기홍 위원] \"저는 지금 답변도 정말 대단히 위험한 답변이라고 생각합니다. 연구윤리를 책임질 교육부장관후보자가 ‘그때그때 달라요’라고 지금 답변한 겁니다.     (영상자료를 보며)  화면 보시면서 말씀드리겠습니다.   표절 플러스 중복게재 플러스 연구비 부당 수령 세 가지가 한꺼번에 있는 연구 부정행위 종합편을 하나 보여드리겠습니다.   화면을 보시면 이것이 한국교육학회 춘계학술대회 2010년입니다 여기에 “교육문제의 해법 : 경제논리와 교육논리 상호보완은 가능한가?”라는 발표문인데 다음 화면을 보시면……    (자료를 들어 보이며)  제가 패널도 따로 만들었습니다마는 여기 발표문을 2010년 12월에 ‘교육과학연구’라는 학회지에 게재를 합니다. 거의 그대로 게재했어요. 그리고 또 2012년 ‘학습자중심 교과교육연구’라는 학회지에 게재를 했는데 이 두 학회지 게재 논문의 중복률이 73%입니다.  이것 명백한 중복게재인데 이것은 중복게재라고 생각하시지요?  답변을 좀 빨리빨리 해 주세요.\"\n교육부장관후보자 김명수] \"반드시 그렇지만도 않다 이렇게 생각이 됩니다.\"\n유기홍 위원] \"예? 뭐라고요?\"\n교육부장관후보자 김명수] \"반드시 그렇지만도 않다 중복게재라고…… 사실은……\"\n",
		"passage_Cnt": 702
	},
	"Annotation": {
		"summary1": "두 학회지 게재 논문의 중복률이 73%인데 이것이 중복 게재라고 생각하냐는 질문에 김 후보자는 반드시 그렇지만도 않다고 생각한다 말했다.",
		"summary2": "교육부장관후보자 김명수] \"반드시 그렇지만도 않다 이렇게 생각이 됩니다.\" 그리고 또 2012년 ‘학습자중심 교과교육연구’라는 학회지에 게재를 했는데 이 두 학회지 게재 논문의 중복률이 73%입니다. 이것 명백한 중복게재인데 이것은 중복게재라고 생각하시지요?",
		"summary3": null,
		"summary_3_cnt": null
	}
}