{
	"Meta(Acqusition)": {
		"doc_id": "REPORT-minute-00031",
		"doc_category": "REPORT",
		"doc_type": "minute",
		"doc_name": "제20대 국회 기획재정위원회 회의록 데이터셋.csv",
		"author": null,
		"publisher": null,
		"publisher_year": null,
		"doc_origin": "국회도서관 포털"
	},
	"Meta(Refine)": {
		"passage_id": "REPORT-minute-00031-02247",
		"passage": "위원장 조경태] \"정무경 기획조정실장 수고하셨습니다.   이종구 위원님 자료 제출 요구가 있습니다.\"\n이종구 위원] \"오전에 더불어민주당 우원식 원내대표께서 발언하시는 과정에서 이런 말씀을 하셨어요. ‘주요 OECD 국가들 또한 2016년 이후 개인소득세 최고세율과 부동산 보유세를 인상하여 지속 가능한 복지의 틀을 구축하고 있다’ 이렇게 얘기했다고요.   부총리 듣는 거예요?\"\n부총리겸기획재정부장관 김동연] \"예 듣고 있습니다.\"\n이종구 위원] \"그래서 첫째 전 OECD 국가들의 2016년 이후의 개인소득세 최고세율 조정 상황 두 번째 부동산 보유세의 조정 상황 이것을 오후에 질의 전까지 보내 주세요.   세제실장!\"\n기획재정부세제실장 최영록] \"예.\"\n이종구 위원] \"듣고 있지?\"\n기획재정부세제실장 최영록] \"예.\"\n이종구 위원] \"정확하게 OECD 국가들이 정말로 개인소득세 최고세율을 올렸는지 그리고 부동산 보유세를 인상했는지 이것을 OECD 전 국가 것을 주라고요 우리나라를 포함해서. 알겠습니까?\"\n부총리겸기획재정부장관 김동연] \"예 하여튼 오후까지 될 수 있을지 모르지만 최선을 다해서 빨리 만들어 보겠습니다.\"\n이종구 위원] \"아니 다 나와 있는 것 아니에요? DB 보면 다 나와 있는 것인데 뭘……\"\n부총리겸기획재정부장관 김동연] \"빨리 찾아보겠습니다.\"\n이종구 위원] \"내세요 이따 오후에.\"\n부총리겸기획재정부장관 김동연] \"예 알겠습니다.\"\n",
		"passage_Cnt": 710
	},
	"Annotation": {
		"summary1": "이 위원은 OECD 국가들의 개인소득세 최고세율과 부동산 보유세 인상에 대한 자료를 요청했고 김 부총리 겸 기획재정부 장관은 최선을 다해 빨리 만들겠다고 했다.",
		"summary2": "이종구 위원] \"정확하게 OECD 국가들이 정말로 개인소득세 최고세율을 올렸는지 그리고 부동산 보유세를 인상했는지 이것을 OECD 전 국가 것을 주라고요 우리나라를 포함해서. 부총리겸기획재정부장관 김동연] \"예 하여튼 오후까지 될 수 있을지 모르지만 최선을 다해서 빨리 만들어 보겠습니다.\"",
		"summary3": null,
		"summary_3_cnt": null
	}
}