{
	"Meta(Acqusition)": {
		"doc_id": "REPORT-minute-00035",
		"doc_category": "REPORT",
		"doc_type": "minute",
		"doc_name": "제20대 국회 법제사법위원회 회의록 데이터셋.csv",
		"author": null,
		"publisher": null,
		"publisher_year": null,
		"doc_origin": "국회도서관 포털"
	},
	"Meta(Refine)": {
		"passage_id": "REPORT-minute-00035-05260",
		"passage": "채이배 위원] \"없습니다.\"\n위원장대리 김도읍] \"없습니까?   국방부차관님 75항 6ㆍ25전쟁 무공훈장 수여 등에 관한 법률안 여기에 지금 인력과 예산이 필요하지요?\"\n국방부차관 서주석] \"예 예산이 필요합니다.\"\n위원장대리 김도읍] \"예산 확보는 차질 없이 될 것 같습니까?\"\n국방부차관 서주석] \"차질 없이 될 수 있습니다.\"\n위원장대리 김도읍] \"차관님이 어떻게 그렇게 장담을 하십니까?\"\n국방부차관 서주석] \"기재부하고 협의를 해서 약 20억 정도 드는데 기재부하고 이미 협의를 했습니다. 동의를 한 사항입니다.\"\n위원장대리 김도읍] \"내년도 본예산에 정부안으로 들어갑니까?\"\n국방부차관 서주석] \"예 당연히 들어갑니다.\"\n위원장대리 김도읍] \"이것은 무공수훈자들에 대한 예우 차원에서라도 법 개정과 함께 반드시 예산이 수반돼야 한다는 말씀을 드립니다.\"\n국방부차관 서주석] \"예 잘 알겠습니다.\"\n위원장대리 김도읍] \"차관님 그러면 무공훈장을 수여하는 작업을 하는데 대상이 어느 정도 될 것 같아요?\"\n국방부차관 서주석] \"저희가 파악하고 있는 것은 5만 6000여 명으로 알고 있습니다.\"\n위원장대리 김도읍] \"지금 기초자료는 다 수집이 됐나요?\"\n국방부차관 서주석] \"예 갖고 있습니다.\"\n위원장대리 김도읍] \"갖고 있습니까? 그러면 이 법만 통과되면 바로 수여 작업을 할 수 있나요?\"\n국방부차관 서주석] \"최대한 연락을 하고 하는 작업을 같이 해야 됩니다. 수여가 바로 되지는 않겠습니다마는 기간 내에 저희가 완료될 수 있도록 노력하겠습니다.\"\n",
		"passage_Cnt": 763
	},
	"Annotation": {
		"summary1": "김 위원장대리는 무공훈장 수여 대상이 어느 정도인지 물었고 서 국방부차관은 5만 6000여 명으로 파악된다고 답했다.",
		"summary2": "위원장대리 김도읍] \"차관님 그러면 무공훈장을 수여하는 작업을 하는데 대상이 어느 정도 될 것 같아요?\" 국방부차관 서주석] \"저희가 파악하고 있는 것은 5만 6000여 명으로 알고 있습니다.\"",
		"summary3": null,
		"summary_3_cnt": null
	}
}