{
	"Meta(Acqusition)": {
		"doc_id": "REPORT-minute-00015",
		"doc_category": "REPORT",
		"doc_type": "minute",
		"doc_name": "제19대 국회 안전행정위원회 회의록 데이터셋.csv",
		"author": null,
		"publisher": null,
		"publisher_year": null,
		"doc_origin": "국회도서관 포털"
	},
	"Meta(Refine)": {
		"passage_id": "REPORT-minute-00015-00386",
		"passage": "안전행정부장관 유정복] \"지금 검찰 수사가 진행 중에 있기 때문에 수사 결과가 나오는 대로 바로 안전행정부에서도 특별감찰을 해서 적의 조치하겠습니다.\"\n김현 위원] \"그런데 그건 아주 상투적인 답변이고요.\"\n안전행정부장관 유정복] \"예?\"\n김현 위원] \"상투적인 답변이라고요. 늘……\"\n안전행정부장관 유정복] \"아니요 현실이 그렇게 할 수밖에 없기 때문에……\"\n김현 위원] \"그런데 이것이 최초에 보도된 것은 2012년 10월이에요 이것이 보도된 것은. 그리고 경찰 특수수사과에서 수사 시작한 것은 올해고요. 그러면 행안부 시절에 이 부분에 대해서 감찰이 이루어졌어야 되는 사안이에요 물론 전임자의 문제이기는 하지만.  그런데 이 사건이 지금 불구속 기소 상태로 되고 있어요. 그리고 액수도 1억 3000만 원이니까 굉장히 큰 액수입니다. 그러니까 1년에 받는 국고보조금 10억 중에 1억 1000만 원이면 10%에 해당하는 금액이에요. 굉장히 큰 액수가 유용이 됐는데 이것이 언론 보도가 나온 것은 2012년 10월이고 그것이 조사가 시작된 건 그 이후라 하더라도 공무원의 기강을 바로 잡기 위해서는 사건이 경찰 수사되기 전에 공무원의 기강을 잡기 위한 노력이 필요한 건 아닌가요?  만약에 유사한……    (발언시간 초과로 마이크 중단)    (마이크 중단 이후 계속 발언한 부분)사례가 또 발생한다고 했을 때에도 경찰이 수사 중인 사건 또는 검찰이 수사 중인 사건이기 때문에 감찰을 않겠다 이것은 좀 바꿔야 되는 것 아닌가요?\"\n",
		"passage_Cnt": 747
	},
	"Annotation": {
		"summary1": "안전행정부장관 유 씨는 검찰 수사 결과가 나오는 대로 안전행정부에서 특별감찰을 해서 적의 조치하겠다고 하자 김 위원은 상투적인 답변이라 말했다.",
		"summary2": "안전행정부장관 유정복] \"지금 검찰 수사가 진행 중에 있기 때문에 수사 결과가 나오는 대로 바로 안전행정부에서도 특별감찰을 해서 적의 조치하겠습니다.\" 김현 위원] \"그런데 그건 아주 상투적인 답변이고요.\"",
		"summary3": null,
		"summary_3_cnt": null
	}
}