{
	"Meta(Acqusition)": {
		"doc_id": "REPORT-minute-00023",
		"doc_category": "REPORT",
		"doc_type": "minute",
		"doc_name": "제19대 국회 환경노동위원회 회의록 데이터셋.csv",
		"author": null,
		"publisher": null,
		"publisher_year": null,
		"doc_origin": "국회도서관 포털"
	},
	"Meta(Refine)": {
		"passage_id": "REPORT-minute-00023-03983",
		"passage": "환경부장관 윤성규] \"답변 올리겠습니다.   정부가 국회에 도전할 수가 없지요. 그것은 아니고……\"\n이인영 위원] \"그러면 환경부만 도전하는 겁니까?\"\n환경부장관 윤성규] \"그건 아니고요. 국익 차원에서 보다 확실한 방법 강제적인 방법인 이 연비나 온실가스 기준으로 이렇게 가면서……\"\n이인영 위원] \"그 기준으로도 97g/㎞로 하겠다고 그랬는데 지금 100g/㎞로 하겠다고 해 가지고 그것보다도 안 맞잖아요?\"\n환경부장관 윤성규] \"그것은 저는 여기서 위원님께 처음 듣고 있습니다. 저희는 97g에 대해서 변동이 없이 지금 계속 업계들하고 대화를 하고 있는 그런……\"\n이인영 위원] \"보조금 지원 기준 대상을 100g/㎞로 하겠다면서요.\"\n환경부장관 윤성규] \"죄송합니다.  제가 말씀 못 들었습니다만……\"\n이인영 위원] \"아니 그냥 말씀하시려고 하셨던 것 하시면 돼요 제가 미루어 짐작컨대.\"\n환경부장관 윤성규] \"100g이라고 하는 것은 보조금 관련해서 말씀하신 것 같은데요 저희가 현재 하이브리드 차가 2.5% 3% 선으로 아주 정체되어 있습니다.   그래서 이 부분을 돌파하기 위해서는 기존의 세제혜택 310만 원……\"\n이인영 위원] \"그것은 아까 다른 위원님 말씀에 대답을 하신 것이고요 제 얘기는 배출가스 기준을 97g/㎞로 하겠다고 했는데 하이브리드 보조금 지원은 100g/㎞로 하겠다고 그러는데 일관성도 없고 정책의 모순이 아니냐 이거예요.\"\n",
		"passage_Cnt": 705
	},
	"Annotation": {
		"summary1": "환경부장관 윤 씨는 연비나 온실가스 기준에 대해 변동 없이 업계들과 97g으로 대화하고 있다고 했다.",
		"summary2": "저희는 97g에 대해서 변동이 없이 지금 계속 업계들하고 대화를 하고 있는 그런…… 국익 차원에서 보다 확실한 방법 강제적인 방법인 이 연비나 온실가스 기준으로 이렇게 가면서…… 환경부장관 윤성규] \"그것은 저는 여기서 위원님께 처음 듣고 있습니다.",
		"summary3": null,
		"summary_3_cnt": null
	}
}