{
	"Meta(Acqusition)": {
		"doc_id": "REPORT-minute-00031",
		"doc_category": "REPORT",
		"doc_type": "minute",
		"doc_name": "제20대 국회 기획재정위원회 회의록 데이터셋.csv",
		"author": null,
		"publisher": null,
		"publisher_year": null,
		"doc_origin": "국회도서관 포털"
	},
	"Meta(Refine)": {
		"passage_id": "REPORT-minute-00031-00803",
		"passage": "위원장 조경태] \"알겠습니다.  김태년 위원장님께서 차분하게 이야기하니까 잘 들립니다.  부총리님 세수추계에 대한 자료 제출 요구를 많은 위원님들께서 하고 계시지 않습니까?\"\n부총리겸기획재정부장관 유일호] \"예.\"\n위원장 조경태] \"거기에 대해서 빠른 시간 내에 해당 위원님들께 자료를 제출해 주시기를 바라고요.\"\n부총리겸기획재정부장관 유일호] \"예 저희가 세목별 세수추계 방법 또 주요 변수 이런 것들은 이미 제출을 해 드렸습니다. 아마 더 추가로 필요하시다면 저희가 제출 가능한 것은 추가로 제출하도록 그렇게 하겠습니다.\"\n위원장 조경태] \"그리고 조선ㆍ해운 구조조정 계획안에 대해서는 10월까지 하시기로 했으니까 아직 시간은 있습니다마는 언제까지 가능한지……\"\n부총리겸기획재정부장관 유일호] \"예 이달 말 10월 31일까지는 보고를 드릴 수 있도록 지금 마지막 손을 보고 있습니다. 꼭 그렇게 하도록 하겠습니다.\"\n위원장 조경태] \"그래서 저희 위원회를 이 부분에 대해서 한 번 더 열겠습니다. 열어서 제대로 된 구조조정 아주 고통스럽겠지만 정말 뼈를 깎는 듯한 그런 구조조정안을 꼭 제출해 주시기 부탁드리겠습니다.\"\n부총리겸기획재정부장관 유일호] \"예 그 마무리를 꼭 빨리 짓고 하여튼 이달 말까지는 꼭 제출하도록 그렇게 하겠습니다.\"\n위원장 조경태] \"수고하셨습니다.  그러면 정해진 질의 순서에 따라서 질의하도록 하겠습니다.  박명재 위원님 질의해 주시기 바랍니다.\"\n",
		"passage_Cnt": 716
	},
	"Annotation": {
		"summary1": "조 위원은 된 조선·해운 구조조정 계획안이 언제까지 가능한지 질문했고 유 부총리는 빨리 마무리 지어서 제출하도록 하겠다고 답변했다.",
		"summary2": "위원장 조경태] \"그리고 조선ㆍ해운 구조조정 계획안에 대해서는 10월까지 하시기로 했으니까 아직 시간은 있습니다마는 언제까지 가능한지……\" 부총리겸기획재정부장관 유일호] \"예 그 마무리를 꼭 빨리 짓고 하여튼 이달 말까지는 꼭 제출하도록 그렇게 하겠습니다.\"",
		"summary3": null,
		"summary_3_cnt": null
	}
}