{
	"Meta(Acqusition)": {
		"doc_id": "REPORT-minute-00032",
		"doc_category": "REPORT",
		"doc_type": "minute",
		"doc_name": "제20대 국회 농림축산식품해양수산위원회 회의록 데이터셋.csv",
		"author": null,
		"publisher": null,
		"publisher_year": null,
		"doc_origin": "국회도서관 포털"
	},
	"Meta(Refine)": {
		"passage_id": "REPORT-minute-00032-02994",
		"passage": "해양수산부장관 김영춘] \"지금도 어촌계 진입장벽 완화와 귀어ㆍ귀촌 활성화를 위해서 관련 법률 개정을 추진하고 있고 동시에 아울러서 지금 말씀하신 어촌계를 지원할 수 있는 그런 센터 설립을 위한 수협법 개정도 추진 중에 있습니다.  그래서 안이 마련이 되면 상반기 중에 국회에 제출할 예정입니다.\"\n위성곤 위원] \"고맙습니다.  적극적으로 좀 일이 이루어졌으면 좋겠습니다.\"\n해양수산부장관 김영춘] \"현재 목표는 2019년 센터 건립을 목표로 해서 추진해 보겠습니다.\"\n위성곤 위원] \"고맙습니다.  아울러서 지난해 국정감사에서 지적한 사항인데요. 어촌계에 대한 어업실태조사를 전국적으로 맞춰서 진행을 해 주십사 하는 부탁의 말씀을 드리겠습니다.\"\n해양수산부장관 김영춘] \"예 알겠습니다.\"\n위성곤 위원] \"청장님.\"\n해양경찰청장 박경민] \"예.\"\n위성곤 위원] \"지난 국감에서 총경의 본청 독점에 대해서 제가 질의를 했었는데요. 이번 인사 개편 방향이 섰나요?\"\n해양경찰청장 박경민] \"예 기본적으로 파출소 함정 근무를 하지 않으면 점수를 객관적으로 만점을 받지 못하도록 그렇게 개선을 했고요. 그래서 지난 연말 총경 승진 때도 함정 근무라든지 또 현장 근무자들을 많이 배려하도록 그렇게 했습니다.\"\n위성곤 위원] \"고맙습니다.  누누이 말씀드리지만 현장 출신들이 실질적 보직을 맡고 일을 할 수 있게끔 현장 출신들을 우대해 주시기 바랍니다.  거점 파출소 관련해서 하나만 말씀을 드리겠는데요. 저희 제주에 한림하고 성산에 돼 있어요. 그런데 한림하고 성산은 거리상……    (발언시간 초과로 마이크 중단)    (마이크 중단 이후 계속 발언한 부분)한 100㎞가 됩니다. 해상으로 120㎞가량 되는데요. 거기서 거기까지 가려면 너무 많이 걸려서 사실은 중간에 서귀포쯤에 서귀항쯤에 하나가 있어야 되지 않겠는가라고 생각이 되어지는데 적극 검토해 주시겠습니까?\"\n",
		"passage_Cnt": 930
	},
	"Annotation": {
		"summary1": "박 해양경찰청장은 기본적으로 파출소 함정 근무를 하지 않으면 만점을 받지 못하도록 개선하고 총경 승진 때도 함정 근무, 현장 근무자들을 많이 배려하도록 했다고 말했다.",
		"summary2": "해양경찰청장 박경민] \"예 기본적으로 파출소 함정 근무를 하지 않으면 점수를 객관적으로 만점을 받지 못하도록 그렇게 개선을 했고요. 그래서 지난 연말 총경 승진 때도 함정 근무라든지 또 현장 근무자들을 많이 배려하도록 그렇게 했습니다.",
		"summary3": null,
		"summary_3_cnt": null
	}
}