{
	"Meta(Acqusition)": {
		"doc_id": "REPORT-minute-00036",
		"doc_category": "REPORT",
		"doc_type": "minute",
		"doc_name": "제20대 국회 보건복지위원회 회의록 데이터셋.csv",
		"author": null,
		"publisher": null,
		"publisher_year": null,
		"doc_origin": "국회도서관 포털"
	},
	"Meta(Refine)": {
		"passage_id": "REPORT-minute-00036-01426",
		"passage": "보건복지부장관 박능후] \"예.\"\n권미혁 위원] \"모든 의학적 비급여를 건강보험이 보장하겠다고 지금 발표했잖아요 8월 9일 날.\"\n보건복지부장관 박능후] \"예 그렇습니다.\"\n권미혁 위원] \"건강보험 보장성이 확대가 되면 국민들도 이익을 보지만 민간의료보험이 반사이익을 본다라는 의견도 많은 거 아시지요?\"\n보건복지부장관 박능후] \"예.\"\n권미혁 위원] \"제가 좀 조사를 해 봤습니다. 2016년 보건사회연구원 연구에서 박근혜정부의 건강보험 보장성 확대 정책으로 민간보험사가 2013년부터 17년까지 어느 정도 반사이익을 얻었다고 생각하시나요?\"\n보건복지부장관 박능후] \"대략 1조 5000억 정도 이렇게 지금 추정을 하고 있습니다.\"\n권미혁 위원] \"예 맞습니다.  박근혜정부 보장성 강화 정책에 대한 누적 소요액이 11조 2590억 원이었고 이번 정부에서 투입하는 소요 금액이 30조잖아요. 그러니까 얼추 해도 거의 한 3배 정도 소요액 규모가 있으니까 민간보험 반사이익이 굉장히 커질 건 자명하지요?\"\n보건복지부장관 박능후] \"예.\"\n권미혁 위원] \"그래서 일단 정확한 실태조사를 통해서 실손보험의 반사이익을 산출하고 준비해야 되지 않겠나 하는 질문을 드리고요. 또 올해 안에 공사 의료보험 정책협의체 구성하겠다고 했는데 협의체 구성하셨나요?\"\n보건복지부장관 박능후] \"지금 아직 협의체는 안 됐지만 그 관련법은 준비를 하고 있습니다.\"\n권미혁 위원] \"2011년부터 개인의료보험 정책협의체 구성해서 협력체계 구축한 바 있지요?\"\n",
		"passage_Cnt": 746
	},
	"Annotation": {
		"summary1": "권 위원은 박 정부의 건강보험 보장성 확대 정책으로 민간 보험사가 2013년부터 17년까지 얼마의 반사이익을 얻었는지 물었고 박 장관은 약 1조 5000억 정도라고 답했다.",
		"summary2": "권미혁 위원] \"제가 좀 조사를 해 봤습니다. 2016년 보건사회연구원 연구에서 박근혜정부의 건강보험 보장성 확대 정책으로 민간보험사가 2013년부터 17년까지 어느 정도 반사이익을 얻었다고 생각하시나요? 보건복지부장관 박능후] \"대략 1조 5000억 정도 이렇게 지금 추정을 하고 있습니다.\"",
		"summary3": null,
		"summary_3_cnt": null
	}
}