{
	"Meta(Acqusition)": {
		"doc_id": "REPORT-minute-00035",
		"doc_category": "REPORT",
		"doc_type": "minute",
		"doc_name": "제20대 국회 법제사법위원회 회의록 데이터셋.csv",
		"author": null,
		"publisher": null,
		"publisher_year": null,
		"doc_origin": "국회도서관 포털"
	},
	"Meta(Refine)": {
		"passage_id": "REPORT-minute-00035-01202",
		"passage": "감사원장 황찬현] \"감사활동에 있어서도 피감사 대상자들의 인권이 철저히 보호되어야 된다는 점은 전적으로 공감을 합니다.\"\n오신환 위원] \"앞서 그러면 반대된 측면에서 정치적 중립과 독립성에 대해서 말씀드리겠습니다.   지금 개헌특위에서 감사원의 소속기관에 대한 개편안이 세 가지 안이 논의되고 있는 것 알고 계신가요?\"\n감사원장 황찬현] \"예 내용 알고 있습니다.\"\n오신환 위원] \"그 의견들에 대해서는 감사원의 입장은 어떤 것이지요?\"\n감사원장 황찬현] \"저희들은 현재 시스템 자체가 여러 가지 문제는 있지만 고쳐서 쓸 수도 있겠다는 생각을 기본적으로 가지고 있습니다마는 그런 부분이 설득력이 별로 없다는 논의가 많이 있습니다. 그런 경우를 대비를 한다면 저희들이 국회에 이관해서 하는 부분은 지금 이 문제가 논의되는 게 주로 감사원의 정치적 독립성이 주된 화두라고 봅니다. 그 측면에서 보면 국회로 이관했을 때 그 부분에 대해서는 상당히 설계하기가 쉽지 않을 것 같다 그걸 보장하기가.   뿐만 아니라 구조적으로 보면 지방자치단체의 운영이 굉장히 방만합니다. 이 점에 대해서 지방자치단체에 지방의회가 있는 마당에 국회 기관이 직접 감사를 한다는 것은 현실적으로 여러 가지 헌법상ㆍ법률상 어려운 문제가 제기됩니다.   뿐만 아니라 감사가 실효성의 문제나 여러 가지나 문제가 제기되어서 그 부분은 얻는 것보다 잃는 것이 많을 가능성이 있다 이렇게 생각됩니다.   그렇다면 현 시스템도 문제가 있다는 걸 전제로 본다면 그런 입장에서는 대안으로 독립 기관으로 가는 것 외에는 다른 방안이 없는 것 아닌가 하는 것이 저희들 전체적인 의견입니다.\"\n",
		"passage_Cnt": 807
	},
	"Annotation": {
		"summary1": "감사원의 소속기관에 대한 개편안이 논의되고 있는 것을 알고 있냐는 질문에 황 감사원장은 내용을 알고 있다고 했다.",
		"summary2": "지금 개헌특위에서 감사원의 소속기관에 대한 개편안이 세 가지 안이 논의되고 있는 것 알고 계신가요? 감사원장 황찬현] \"예 내용 알고 있습니다.\"",
		"summary3": null,
		"summary_3_cnt": null
	}
}