{
	"Meta(Acqusition)": {
		"doc_id": "REPORT-minute-00031",
		"doc_category": "REPORT",
		"doc_type": "minute",
		"doc_name": "제20대 국회 기획재정위원회 회의록 데이터셋.csv",
		"author": null,
		"publisher": null,
		"publisher_year": null,
		"doc_origin": "국회도서관 포털"
	},
	"Meta(Refine)": {
		"passage_id": "REPORT-minute-00031-02867",
		"passage": "기획재정부제1차관 고형권] \"비관이나 낙관이라기보다도 매우 엄중하게 결코 이게……\"\n엄용수 위원] \"예상을 그래도 어떻게 한다는 식견이 있을 것 아닙니까? 어떻게 보십니까?\"\n기획재정부제1차관 고형권] \"쉽게 고치기는 어려운 부분이고 그래서 정책적 노력이 매우 중요하다고 생각하고요.  위원님 방금 이 다음에 어떤 지표에서 문제가 생길 것이냐 말씀하셨는데 정부도 비슷한 문제의식을 가지고 많은 검토를 해 가지고……\"\n엄용수 위원] \"책임은 기재부가 지는 겁니다 집행부니까 행정부니까. 그래서 만일에 연말까지 갔는데도 개선되지 않거나 또는 더 나빠지면 기재부가 정말 식견이 없어서 또는 거짓말쟁이로 낙인찍히는 결과를 빚을 겁니다.   그래서 이게 개선된다는 자신이 없으면 재정을 투입해서 쓰는 방법이 개선된다는 확신이 없으면 지금 그만둬야 되는 거지요. 나중에 몇 달 후에 네 달 다섯 달 후에 그걸 확인할 수 있을 것 같으면 그때는 지표도 나빠지고 또 재정은 재정대로 날려 버리고 그것 누가 책임집니까? 여러분들은 그것 엎었으면 그만입니까?  그다음의 책임은 그런 재정을 낭비한 또 더 고통을 분담한 그런 결과에 대해서 누가 책임지느냐 이거지요. 대통령이 별도로 책임진다고 혹시 말씀하셨습니까? 그런 것 아니잖아요?  확신이 없으면 안 해야지요. 왜 그걸 자꾸 갖고 가느냐 이거지요. 방향이 틀린 거잖아요. 여러분들 아시잖아요? 정치적 논리 때문에 정확하게 이야기하면 이념 때문에 그렇지 않습니까? 어떻게 생각하십니까?\"\n",
		"passage_Cnt": 740
	},
	"Annotation": {
		"summary1": "엄 위원은 개선되지 않거나 더 나빠지면 집행부인 기재부의 책임이라고 말했다.",
		"summary2": "엄용수 위원] \"책임은 기재부가 지는 겁니다 집행부니까 행정부니까. 그래서 만일에 연말까지 갔는데도 개선되지 않거나 또는 더 나빠지면 기재부가 정말 식견이 없어서 또는 거짓말쟁이로 낙인찍히는 결과를 빚을 겁니다.",
		"summary3": null,
		"summary_3_cnt": null
	}
}