{
	"Meta(Acqusition)": {
		"doc_id": "REPORT-minute-00035",
		"doc_category": "REPORT",
		"doc_type": "minute",
		"doc_name": "제20대 국회 법제사법위원회 회의록 데이터셋.csv",
		"author": null,
		"publisher": null,
		"publisher_year": null,
		"doc_origin": "국회도서관 포털"
	},
	"Meta(Refine)": {
		"passage_id": "REPORT-minute-00035-03549",
		"passage": "법무부장관 박상기] \"전혀 그렇게 돼서는 안 됩니다.\"\n채이배 위원] \"제가 법무부를 통해서 받은 법조 공무원 직무 관련 범죄 기소 현황 자료를 보니까요. 뇌물 수수 공금 횡령 직권 남용 같은 직무 관련 범죄를 저지른 검찰ㆍ법무부ㆍ법원 공무원들의 직무 관련 범죄로 1만 건이 넘는 입건이 있었는데 이중에 48건만 기소됐답니다. 그런데 일반 공무원도 똑같은 직무범죄에 대해서 약 2만 건이 있었는데 여기는 862건이 기소가 됐어요. 즉 법조 공무원은 0.45%만 기소됐고 일반 공무원은 4.3%로 10배 넘게 더 기소가 돼요.   이게 혹시 제 식구 감싸기 아닌가 싶은데 어떻게 평가하세요?\"\n법무부장관 박상기] \"계량적으로만 가지고 평가할 수는 없지만 제 식구 감싸기는 있어서도 안 되고요. 앞으로 그런 일이 없도록 하겠습니다.\"\n채이배 위원] \"그래서 그런 일이 없도록 하고자 하는 게 저는 공수처가 반드시 도입되어야 된다고 생각합니다.\"\n법무부장관 박상기] \"예 맞습니다.\"\n채이배 위원] \"앞서 다른 위원님들도 공수처에 대해서 많이 말씀을 해 주셨는데 정부가 그렇게 입장만 내고 법안도 내지 않고 마치 할 일을 다했다라고 지금 손 놓고 있는 모습은 제가 보기에는 굉장히 임무를 방기하고 있다라고 생각하고요. 보다 적극적인 입장 자세를 가져주시기를 촉구합니다.\"\n법무부장관 박상기] \"알겠습니다.\"\n위원장 여상규] \"수고하셨습니다.   다음으로 존경하는 박지원 위원님 질의하시기 바랍니다.\"\n",
		"passage_Cnt": 725
	},
	"Annotation": {
		"summary1": "채 위원은 법조 공무원이 0.45% 기소됐고 일반 공무원은 4.3%로 10배 넘게 기소됐다 말하며 그런 일이 없도록 하고자 공수처가 도입되어야 한다고 했다.",
		"summary2": "채이배 위원] \"제가 법무부를 통해서 받은 법조 공무원 직무 관련 범죄 기소 현황 자료를 보니까요. 채이배 위원] \"그래서 그런 일이 없도록 하고자 하는 게 저는 공수처가 반드시 도입되어야 된다고 생각합니다.\" 즉 법조 공무원은 0.45%만 기소됐고 일반 공무원은 4.3%로 10배 넘게 더 기소가 돼요.",
		"summary3": null,
		"summary_3_cnt": null
	}
}