{
	"Meta(Acqusition)": {
		"doc_id": "REPORT-minute-00031",
		"doc_category": "REPORT",
		"doc_type": "minute",
		"doc_name": "제20대 국회 기획재정위원회 회의록 데이터셋.csv",
		"author": null,
		"publisher": null,
		"publisher_year": null,
		"doc_origin": "국회도서관 포털"
	},
	"Meta(Refine)": {
		"passage_id": "REPORT-minute-00031-04062",
		"passage": "박명재 위원] \"아니 삶의 질을 측정하는 데 기본적인 지표가 지니계수 아닙니까?\"\n통계청장 강신욱] \"지니계수와 상대 빈곤률이 둘 다 빈곤 관련 지표이기는 하지만 삶의 질을 나타낼 때는 국민들이 빈곤의 위험에 얼마나 더 노출되어 있느냐가 좀 더 적절하다고 판단했던 것으로 이해하고 있습니다.\"\n박명재 위원] \"이렇게 새로 바꾸어 가지고 발표를 했는데 바꾸기 전의 기존 지표 있지 않습니까 80개 지표? 그것을 가지고 다시 한번 해 보세요. 하면 지금 바뀐 새로운 지표와 차이가 얼마나 나는지 동등한 비슷한 유형을 한다면 통계에 신뢰가 가는 것이고 한번 해 보셨습니까?\"\n통계청장 강신욱] \"예 해 보았습니다.\"\n박명재 위원] \"어떻게 나타나요?\"\n통계청장 강신욱] \"구지표로 그대로 적용했을 때는 지표개선 비율이 74.0%였습니다. 그리고 신지표로 했을 때는 76.1%여서 두 지표체계를 모두 다 봤을 때 큰 폭으로 증가했는데 물론 신 지표로 했을 때가 한 2.1%p 정도 더 증가하는 것으로 나타났습니다. 그런데 전체적인 지표개선 비율이 12%였기 때문에 사실은 지표개선에 의한 효과보다는 시점변화에 따른 효과 전체적인 지표개선 추이에 따른 효과가 더 큰 것으로 판단하고 있습니다.\"\n박명재 위원] \"기존 지표하고 새로 한 지표하고 차이점 유사점을 저한테 보고 좀 해 주세요.\"\n통계청장 강신욱] \"예 그러겠습니다.\"\n박명재 위원] \"내주시고요.\"\n",
		"passage_Cnt": 700
	},
	"Annotation": {
		"summary1": "박 위원이 지니계수와 바뀐 새로운 지표가 얼마나 차이가 나는지를 확인해 보라고 하자 강 통계청장은 구지표로 적용했을 때 지표개선 비율이 74.0%라고 했다.",
		"summary2": "박명재 위원] \"아니 삶의 질을 측정하는 데 기본적인 지표가 지니계수 아닙니까?\" 하면 지금 바뀐 새로운 지표와 차이가 얼마나 나는지 동등한 비슷한 유형을 한다면 통계에 신뢰가 가는 것이고 한번 해 보셨습니까? 통계청장 강신욱] \"구지표로 그대로 적용했을 때는 지표개선 비율이 74.0%였습니다.",
		"summary3": null,
		"summary_3_cnt": null
	}
}