{
	"Meta(Acqusition)": {
		"doc_id": "REPORT-minute-00035",
		"doc_category": "REPORT",
		"doc_type": "minute",
		"doc_name": "제20대 국회 법제사법위원회 회의록 데이터셋.csv",
		"author": null,
		"publisher": null,
		"publisher_year": null,
		"doc_origin": "국회도서관 포털"
	},
	"Meta(Refine)": {
		"passage_id": "REPORT-minute-00035-01299",
		"passage": "위원장 권성동] \"그러면 제가 좀 조정을 하도록 그렇게 하겠습니다.\"\n박범계 위원] \"1분만……\"\n위원장 권성동] \"예 박범계 위원님.\"\n박범계 위원] \"참 격세지감을 느낍니다. 제가 국회의원이 되기 전에 이명박 대통령 때 종편방송 허가와 관련해서 제가―저희 당 그때 정세균 대표 시절이었는데요―싸울 때 저는 원외에서 함께 정말 열심히 싸웠습니다.  그러던 종편이 오늘날 우리 존경하는 여당 위원님을 통해서 ‘믿을 수 없는 방송’…… 격세지감을 참으로 느낍니다. 아마도 이것이 지난 10월 달 즈음부터 지금까지 이어 온 여러 농단과 관련된 그 후과라고 생각을 합니다.  우리 존경하는 금태섭 위원님이 적절히 지적했듯이 과거의 기준이 있었습니다. 그러나 그 뒤에 새로운 기준이 생겼고 새로운 상황이 만들어졌습니다. 충분히 안행위 위원님들이 여러 가지 선거와 관련된 상황들을 십분 백이십분 다 이해하고 그러한 전제하에서 이 법안들이 통과가 되어 온 것입니다.   그런 측면에서 저는 전부 통과가 바람직하다고 보여지지만 굳이 최초에 지적했던 종편 방송의 선거방송과 관련된 부분을 지적했으니까 그 부분은 잠시 어쩌면 내일모레 전체회의를 다시 해야 되니까요 그때로 넘겨 놓고 오늘은 모쪼록 우리 안행위에서 첨예한 사안이었는데 통과시킨 이 재외국민 투표권 부여 문제 이것은 통과시키기를 바랍니다.  실제로 안행위 간사분들께 물어보니까 이렇게 분리해서 통과해도 문제가 되지 않는다고 동의를 받았습니다.\"\n",
		"passage_Cnt": 723
	},
	"Annotation": {
		"summary1": "박 위원은 안행위 위원들이 선거와 관련된 상황들을 이해하여 법안들이 통과되어 온 것이니 전부가 통과되는 것이 바람직하다고 말했다.",
		"summary2": "충분히 안행위 위원님들이 여러 가지 선거와 관련된 상황들을 십분 백이십분 다 이해하고 그러한 전제하에서 이 법안들이 통과가 되어 온 것입니다. 박범계 위원] \"참 격세지감을 느낍니다. 그런 측면에서 저는 전부 통과가 바람직하다고 보여지지만 굳이 최초에 지적했던 종편 방송의 선거방송과 관련된 부분을 지적했으니까 그 부분은 잠시 어쩌면 내일모레 전체회의를 다시 해야 되니까요 그때로 넘겨 놓고 오늘은 모쪼록 우리 안행위에서 첨예한 사안이었는데 통과시킨 이 재외국민 투표권 부여 문제 이것은 통과시키기를 바랍니다.",
		"summary3": null,
		"summary_3_cnt": null
	}
}