{
	"Meta(Acqusition)": {
		"doc_id": "REPORT-minute-00032",
		"doc_category": "REPORT",
		"doc_type": "minute",
		"doc_name": "제20대 국회 농림축산식품해양수산위원회 회의록 데이터셋.csv",
		"author": null,
		"publisher": null,
		"publisher_year": null,
		"doc_origin": "국회도서관 포털"
	},
	"Meta(Refine)": {
		"passage_id": "REPORT-minute-00032-04001",
		"passage": "해양수산부장관후보자 문성혁] \"아까도 말씀을 드렸습니다마는 저희 딸아이가 당시 다니던 중학교에서 다른 중학교로 전학하는 과정에서 발생한 전입신고고요. 이유 여하를 막론하고 그런 행위가 있었다는 것에 대해서 다시 한번 송구스럽게 생각합니다.\"\n손금주 위원] \"그러니까 지금 3건의 주민등록법 위반에 대해서는 인정을 하시는 거지요? 그리고 그 부분에 대해서는 어쨌든 목적이 한 가지였지만 죄송하다 이렇게 제가 정리하면 되겠습니까?\"\n해양수산부장관후보자 문성혁] \"예 사실은 한 번의 전학을 위한 건데요……\"\n손금주 위원] \"그러니까 제가 인정을 한다고요. 한 번의 전학을 위한 거였는데 사정이 이러다 보니까 세 번에 걸쳐서 주소 이전이 있었다……\"\n해양수산부장관후보자 문성혁] \"기록상으로는 세 번째 것은 저희가 옮긴 게 아니고……\"\n손금주 위원] \"아니 법률적으로 얘기하면 이것은 목적범이 아니기 때문에 한 번의 그러니까 우리가 법률적으로 포괄일죄가 되지 않고 3건의 위반이 되는 거예요. 그런데 그것에 대해서 제가 말씀드리지 않았습니까. 후보자께서 정확하게 말씀을 해 주시면 저도 더 이상 문제 삼지 않겠다는 것으로 얘기를 드렸잖아요. 그것을 답변하는데 그렇게 어렵게 답변하세요?  목적에 대해서는 한 가지라고 생각을 하고 이전은 세 번 있었기 때문에 그 부분에 대해서는 국민들한테 송구하다는 말씀을 하시는 거지요?\"\n해양수산부장관후보자 문성혁] \"예 송구스럽게 생각합니다. 다시 한번 송구스러운 말……\"\n",
		"passage_Cnt": 731
	},
	"Annotation": {
		"summary1": "손 위원은 3건의 주민등록법 위반에 대한 사죄를 요구했고 문 해양수산부장관후보자는 송구하다고 했다.",
		"summary2": "손금주 위원] \"그러니까 지금 3건의 주민등록법 위반에 대해서는 인정을 하시는 거지요? 그리고 그 부분에 대해서는 어쨌든 목적이 한 가지였지만 죄송하다 이렇게 제가 정리하면 되겠습니까? 해양수산부장관후보자 문성혁] \"예 송구스럽게 생각합니다.",
		"summary3": null,
		"summary_3_cnt": null
	}
}